{
    "mobileBottomRow": 34,
    "widgetName": "Text3",
    "displayName": "Text",
    "iconSVG": "/static/media/icon.a47d6d5dbbb718c4dc4b2eb4f218c1b7.svg",
    "searchTags": [
        "typography",
        "paragraph",
        "label"
    ],
    "topRow": 30,
    "bottomRow": 34,
    "parentRowSpace": 10,
    "type": "TEXT_WIDGET",
    "hideCard": false,
    "mobileRightColumn": 15,
    "animateLoading": true,
    "overflow": "NONE",
    "fontFamily": "{{appsmith.theme.fontFamily.appFont}}",
    "parentColumnSpace": 8.41015625,
    "dynamicTriggerPathList": [],
    "leftColumn": 0,
    "dynamicBindingPathList": [
        {"key": "truncateButtonColor"},
        {"key": "fontFamily"},
        {"key": "borderRadius"}
    ],
    "shouldTruncate": false,
    "truncateButtonColor": "{{appsmith.theme.colors.primaryColor}}",
    "text": "Work",
    "key": "qbfq1alz9v",
    "isDeprecated": false,
    "rightColumn": 15,
    "textAlign": "LEFT",
    "dynamicHeight": "AUTO_HEIGHT",
    "widgetId": "w1ziqrrkiw",
    "minWidth": 450,
    "isVisible": true,
    "fontStyle": "BOLD",
    "textColor": "#231F20",
    "version": 1,
    "parentId": "f54psg59p8",
    "tags": [
        "Suggested",
        "Content"
    ],
    "renderMode": "CANVAS",
    "isLoading": false,
    "mobileTopRow": 30,
    "responsiveBehavior": "fill",
    "originalTopRow": 30,
    "borderRadius": "{{appsmith.theme.borderRadius.appBorderRadius}}",
    "mobileLeftColumn": 0,
    "maxDynamicHeight": 9000,
    "originalBottomRow": 35,
    "fontSize": "1rem",
    "minDynamicHeight": 4
}